anemoi/graphs/__init__.py
anemoi/graphs/__main__.py
anemoi/graphs/_version.py
anemoi/graphs/create.py
anemoi/graphs/describe.py
anemoi/graphs/export.py
anemoi/graphs/inspect.py
anemoi/graphs/normalise.py
anemoi/graphs/utils.py
anemoi/graphs/commands/__init__.py
anemoi/graphs/commands/create.py
anemoi/graphs/commands/describe.py
anemoi/graphs/commands/export_to_sparse.py
anemoi/graphs/commands/inspect.py
anemoi/graphs/edges/__init__.py
anemoi/graphs/edges/attributes.py
anemoi/graphs/edges/directional.py
anemoi/graphs/edges/builders/__init__.py
anemoi/graphs/edges/builders/base.py
anemoi/graphs/edges/builders/cutoff.py
anemoi/graphs/edges/builders/healpix.py
anemoi/graphs/edges/builders/icon.py
anemoi/graphs/edges/builders/knn.py
anemoi/graphs/edges/builders/masking.py
anemoi/graphs/edges/builders/multi_scale.py
anemoi/graphs/generate/__init__.py
anemoi/graphs/generate/healpix.py
anemoi/graphs/generate/hex_icosahedron.py
anemoi/graphs/generate/icon_mesh.py
anemoi/graphs/generate/masks.py
anemoi/graphs/generate/multi_scale_edges.py
anemoi/graphs/generate/transforms.py
anemoi/graphs/generate/tri_icosahedron.py
anemoi/graphs/generate/utils.py
anemoi/graphs/nodes/__init__.py
anemoi/graphs/nodes/attributes/__init__.py
anemoi/graphs/nodes/attributes/area_weights.py
anemoi/graphs/nodes/attributes/base_attributes.py
anemoi/graphs/nodes/attributes/boolean_op.py
anemoi/graphs/nodes/attributes/masks.py
anemoi/graphs/nodes/builders/__init__.py
anemoi/graphs/nodes/builders/base.py
anemoi/graphs/nodes/builders/from_file.py
anemoi/graphs/nodes/builders/from_healpix.py
anemoi/graphs/nodes/builders/from_icon.py
anemoi/graphs/nodes/builders/from_reduced_gaussian.py
anemoi/graphs/nodes/builders/from_refined_icosahedron.py
anemoi/graphs/nodes/builders/from_vectors.py
anemoi/graphs/plotting/__init__.py
anemoi/graphs/plotting/displots.py
anemoi/graphs/plotting/interactive_2d_html.py
anemoi/graphs/plotting/interactive_3d.html.jinja
anemoi/graphs/plotting/interactive_3d_html.py
anemoi_graphs-0.8.3.dist-info/licenses/LICENSE
anemoi_graphs-0.8.3.dist-info/METADATA
anemoi_graphs-0.8.3.dist-info/WHEEL
anemoi_graphs-0.8.3.dist-info/entry_points.txt
anemoi_graphs-0.8.3.dist-info/top_level.txt
anemoi_graphs-0.8.3.dist-info/RECORD
