Metadata-Version: 2.4
Name: anemoi-graphs
Version: 0.8.3
Summary: A package to build graphs for data-driven forecasts.
Author-email: "European Centre for Medium-Range Weather Forecasts (ECMWF)" <software.support@ecmwf.int>
License:                                  Apache License
Project-URL: Documentation, https://anemoi-graphs.readthedocs.io/
Project-URL: Homepage, https://github.com/ecmwf/anemoi-graphs/
Project-URL: Issues, https://github.com/ecmwf/anemoi-graphs/issues
Project-URL: Repository, https://github.com/ecmwf/anemoi-graphs/
Keywords: ai,graphs,tools
Classifier: Development Status :: 4 - Beta
Classifier: Intended Audience :: Developers
Classifier: License :: OSI Approved :: Apache Software License
Classifier: Operating System :: OS Independent
Classifier: Programming Language :: Python :: 3 :: Only
Classifier: Programming Language :: Python :: 3.10
Classifier: Programming Language :: Python :: 3.11
Classifier: Programming Language :: Python :: 3.12
Classifier: Programming Language :: Python :: Implementation :: CPython
Classifier: Programming Language :: Python :: Implementation :: PyPy
Requires-Python: >=3.10
License-File: LICENSE
Requires-Dist: anemoi-utils>=0.4.11
Requires-Dist: hydra-core>=1.3
Requires-Dist: matplotlib>=3.6
Requires-Dist: networkx>=3.1
Requires-Dist: numpy>=1.26
Requires-Dist: plotly>=5.19
Requires-Dist: scikit-learn>=1.5
Requires-Dist: torch>=2.2
Requires-Dist: torch-geometric>=2.3.1
Requires-Dist: typeguard>=4
Provides-Extra: all
Requires-Dist: anemoi-graphs[anemoi,healpix,hex,tri]; extra == "all"
Provides-Extra: anemoi
Requires-Dist: anemoi-datasets>=0.5.21; extra == "anemoi"
Provides-Extra: dev
Requires-Dist: anemoi-graphs[docs,tests]; extra == "dev"
Provides-Extra: docs
Requires-Dist: nbsphinx; extra == "docs"
Requires-Dist: pandoc; extra == "docs"
Requires-Dist: requests; extra == "docs"
Requires-Dist: sphinx<8.2; python_version < "3.11" and extra == "docs"
Requires-Dist: sphinx>=8.2; python_version >= "3.11" and extra == "docs"
Requires-Dist: sphinx-argparse; extra == "docs"
Requires-Dist: sphinx-rtd-theme; extra == "docs"
Requires-Dist: termcolor; extra == "docs"
Requires-Dist: tomli; extra == "docs"
Provides-Extra: healpix
Requires-Dist: healpy>=1.17; extra == "healpix"
Provides-Extra: hex
Requires-Dist: h3<4,>=3.7.7; extra == "hex"
Provides-Extra: tests
Requires-Dist: hypothesis>=6.11; extra == "tests"
Requires-Dist: pytest>=8; extra == "tests"
Requires-Dist: pytest-mock>=3; extra == "tests"
Provides-Extra: tri
Requires-Dist: trimesh>=4.1; extra == "tri"
Provides-Extra: xarray
Requires-Dist: netcdf4<1.7.3,>1.7; extra == "xarray"
Requires-Dist: xarray; extra == "xarray"
Requires-Dist: zarr<3; extra == "xarray"
Dynamic: license-file
